xweights/__init__.py
xweights/_domains_old.py
xweights/_geometry.py
xweights/_io_old.py
xweights/_parser_old.py
xweights/_regions.py
xweights/_tabulator.py
xweights/_weightings.py
xweights/cli_old.py
xweights/data.py
xweights/xweights.py
xweights/data/netcdf/tas_EUR-11_MIROC-MIROC5_rcp85_r1i1p1_CLMcom-CCLM4-8-17_v1_mon_200701-200712.nc
xweights/data/shp/Seewinkel.cpg
xweights/data/shp/Seewinkel.dbf
xweights/data/shp/Seewinkel.prj
xweights/data/shp/Seewinkel.shp
xweights/data/shp/Seewinkel.shx
xweights-0.3.0.dist-info/AUTHORS.rst
xweights-0.3.0.dist-info/LICENSE
xweights-0.3.0.dist-info/METADATA
xweights-0.3.0.dist-info/WHEEL
xweights-0.3.0.dist-info/top_level.txt
xweights-0.3.0.dist-info/RECORD
