Metadata-Version: 2.1
Name: xweights
Version: 0.3.0
Summary: Python xweights contains functionsto create grid weighted area means
Home-page: https://github.com/ludwiglierhammer/xweights
Author: Ludwig Lierhammer
Author-email: ludwig.lierhammer@hereon.de
License: MIT license
Keywords: xweights
Classifier: Development Status :: 2 - Pre-Alpha
Classifier: Intended Audience :: Developers
Classifier: License :: OSI Approved :: MIT License
Classifier: Natural Language :: English
Classifier: Programming Language :: Python :: 3
Classifier: Programming Language :: Python :: 3.8
Classifier: Programming Language :: Python :: 3.9
Classifier: Programming Language :: Python :: 3.10
Requires-Python: >=3.6
License-File: LICENSE
License-File: AUTHORS.rst
Requires-Dist: dask (>=2021.9.1)
Requires-Dist: geopandas (>=0.10.0)
Requires-Dist: xarray (>=0.19.0)
Requires-Dist: pyhomogenize (>=0.2.2)
Requires-Dist: py-cordex (>=0.5.1)
